{
  "timestamp": "2026-07-20T20:21:00.246609",
  "date_range": {
    "days_back": 30,
    "from_date": "2026-06-20",
    "to_date": "2026-07-20",
    "compare_from": null,
    "compare_to": null
  },
  "toast": {},
  "sevenrooms": {
    "reservations": {
      "total_reservations": 224,
      "total_covers": 1493,
      "no_shows": 9,
      "cancellations": 30,
      "completed": 185,
      "vip_count": 4,
      "total_revenue": 44185.74,
      "total_gross_revenue": 56017.76,
      "total_prepayment": 1014.28,
      "avg_party_size": 6.7,
      "avg_duration_min": 139.0,
      "by_server": {
        "Florencio": {
          "reservations": 33,
          "covers": 279,
          "revenue": 9889.0
        },
        "Drilon": {
          "reservations": 17,
          "covers": 120,
          "revenue": 8926.560000000001
        },
        "Daniel": {
          "reservations": 41,
          "covers": 328,
          "revenue": 8923.08
        },
        "Ana": {
          "reservations": 25,
          "covers": 91,
          "revenue": 4244.5
        },
        "Errol": {
          "reservations": 16,
          "covers": 72,
          "revenue": 3337.04
        },
        "Angela": {
          "reservations": 8,
          "covers": 40,
          "revenue": 2975.56
        },
        "Gabi": {
          "reservations": 10,
          "covers": 62,
          "revenue": 2095.0
        },
        "Fab": {
          "reservations": 8,
          "covers": 137,
          "revenue": 1193.0
        },
        "Junior": {
          "reservations": 5,
          "covers": 22,
          "revenue": 614.0
        },
        "Chris Luna": {
          "reservations": 7,
          "covers": 32,
          "revenue": 282.0
        },
        "Grace": {
          "reservations": 5,
          "covers": 39,
          "revenue": 0.0
        },
        "Jess": {
          "reservations": 5,
          "covers": 19,
          "revenue": 0.0
        }
      },
      "by_day": {
        "2026-06-20": {
          "reservations": 25,
          "covers": 191,
          "revenue": 7663.0599999999995
        },
        "2026-07-03": {
          "reservations": 7,
          "covers": 37,
          "revenue": 1048.0
        },
        "2026-06-27": {
          "reservations": 15,
          "covers": 128,
          "revenue": 5004.52
        },
        "2026-07-18": {
          "reservations": 11,
          "covers": 49,
          "revenue": 2828.0
        },
        "2026-07-17": {
          "reservations": 41,
          "covers": 190,
          "revenue": 4935.52
        },
        "2026-06-21": {
          "reservations": 42,
          "covers": 237,
          "revenue": 5030.0
        },
        "2026-07-02": {
          "reservations": 10,
          "covers": 54,
          "revenue": 2104.52
        },
        "2026-06-25": {
          "reservations": 7,
          "covers": 53,
          "revenue": 572.52
        },
        "2026-07-04": {
          "reservations": 1,
          "covers": 13,
          "revenue": 0.0
        },
        "2026-07-10": {
          "reservations": 8,
          "covers": 80,
          "revenue": 3019.04
        },
        "2026-06-26": {
          "reservations": 11,
          "covers": 71,
          "revenue": 4645.04
        },
        "2026-07-16": {
          "reservations": 6,
          "covers": 28,
          "revenue": 1023.0
        },
        "2026-07-12": {
          "reservations": 7,
          "covers": 97,
          "revenue": 597.0
        },
        "2026-07-11": {
          "reservations": 10,
          "covers": 43,
          "revenue": 1569.52
        },
        "2026-07-14": {
          "reservations": 1,
          "covers": 21,
          "revenue": 81.0
        },
        "2026-07-09": {
          "reservations": 4,
          "covers": 16,
          "revenue": 0.0
        },
        "2026-07-08": {
          "reservations": 2,
          "covers": 4,
          "revenue": 115.0
        },
        "2026-06-23": {
          "reservations": 2,
          "covers": 9,
          "revenue": 364.0
        },
        "2026-07-05": {
          "reservations": 2,
          "covers": 13,
          "revenue": 0.0
        },
        "2026-06-28": {
          "reservations": 3,
          "covers": 52,
          "revenue": 2205.0
        },
        "2026-07-01": {
          "reservations": 3,
          "covers": 54,
          "revenue": 830.0
        },
        "2026-07-19": {
          "reservations": 4,
          "covers": 48,
          "revenue": 417.0
        },
        "2026-07-15": {
          "reservations": 1,
          "covers": 3,
          "revenue": 134.0
        },
        "2026-06-30": {
          "reservations": 1,
          "covers": 2,
          "revenue": 0.0
        }
      },
      "by_shift": {
        "DINNER": {
          "reservations": 166,
          "covers": 1046,
          "revenue": 35936.740000000005
        },
        "BRUNCH": {
          "reservations": 58,
          "covers": 447,
          "revenue": 8249.0
        }
      },
      "by_seating_area": {
        "Patio 1": {
          "reservations": 12,
          "covers": 46,
          "revenue": 2870.52
        },
        "Main Dining": {
          "reservations": 153,
          "covers": 748,
          "revenue": 31694.220000000005
        },
        "Unknown": {
          "reservations": 26,
          "covers": 434,
          "revenue": 4573.0
        },
        "G Room": {
          "reservations": 10,
          "covers": 116,
          "revenue": 1584.0
        },
        "Poolside VIP Nightlife Table": {
          "reservations": 10,
          "covers": 58,
          "revenue": 0.0
        },
        "Patio 2": {
          "reservations": 2,
          "covers": 11,
          "revenue": 0.0
        },
        "Grand Ballroom (Mulino\u2019s)": {
          "reservations": 2,
          "covers": 7,
          "revenue": 0.0
        },
        "PDR": {
          "reservations": 5,
          "covers": 56,
          "revenue": 3171.0
        },
        "Bar": {
          "reservations": 2,
          "covers": 7,
          "revenue": 0.0
        },
        "Lounge": {
          "reservations": 2,
          "covers": 10,
          "revenue": 293.0
        }
      },
      "by_reservation_type": {
        "Patio requested": {
          "reservations": 17,
          "covers": 58,
          "revenue": 1759.52
        },
        "Standard": {
          "reservations": 98,
          "covers": 506,
          "revenue": 13287.54
        },
        "Celebration Package (unpaid)": {
          "reservations": 10,
          "covers": 89,
          "revenue": 4652.04
        },
        "Father's Day": {
          "reservations": 10,
          "covers": 58,
          "revenue": 1562.0
        },
        "Father's Day, Patio requested": {
          "reservations": 7,
          "covers": 36,
          "revenue": 0.0
        },
        "Patio requested, Father's Day, Comp check (Lou Jr)": {
          "reservations": 1,
          "covers": 4,
          "revenue": 0.0
        },
        "Graduation": {
          "reservations": 2,
          "covers": 50,
          "revenue": 168.0
        },
        "Birthday, Patio requested, Female birthday": {
          "reservations": 1,
          "covers": 4,
          "revenue": 0.0
        },
        "G Room buyout, Birthday": {
          "reservations": 1,
          "covers": 40,
          "revenue": 907.0
        },
        "Requests Bottle Service": {
          "reservations": 1,
          "covers": 2,
          "revenue": 0.0
        },
        "Birthday": {
          "reservations": 8,
          "covers": 54,
          "revenue": 2309.0
        },
        "#GiganteThursdays": {
          "reservations": 4,
          "covers": 10,
          "revenue": 446.0
        },
        "Patio requested, Birthday": {
          "reservations": 3,
          "covers": 13,
          "revenue": 326.0
        },
        "Celebration": {
          "reservations": 2,
          "covers": 8,
          "revenue": 264.0
        },
        "Birthday, Celebration Package (unpaid)": {
          "reservations": 3,
          "covers": 21,
          "revenue": 1259.56
        },
        "Celebration Package (paid), Patio requested": {
          "reservations": 2,
          "covers": 16,
          "revenue": 1535.0
        },
        "Patio requested, Father's Day": {
          "reservations": 4,
          "covers": 14,
          "revenue": 0.0
        },
        "Anniversary, Patio requested, Dairy-free, Eggs, Lactose Intolerant, Milk": {
          "reservations": 1,
          "covers": 2,
          "revenue": 0.0
        },
        "Female birthday, PDR - Buyout": {
          "reservations": 1,
          "covers": 21,
          "revenue": 81.0
        },
        "Female birthday": {
          "reservations": 2,
          "covers": 6,
          "revenue": 199.0
        },
        "VIP Table/Bottle Service (preselected)": {
          "reservations": 2,
          "covers": 17,
          "revenue": 0.0
        },
        "Birthday, Patio requested": {
          "reservations": 1,
          "covers": 2,
          "revenue": 0.0
        },
        "Engagement": {
          "reservations": 1,
          "covers": 70,
          "revenue": 597.0
        },
        "Cake in fridge": {
          "reservations": 1,
          "covers": 10,
          "revenue": 479.0
        },
        "DJ Event": {
          "reservations": 1,
          "covers": 6,
          "revenue": 0.0
        },
        "Patio requested, Celebration Package (unpaid)": {
          "reservations": 1,
          "covers": 3,
          "revenue": 231.52
        },
        "Anniversary": {
          "reservations": 2,
          "covers": 4,
          "revenue": 275.0
        },
        "Celebration Package (paid)": {
          "reservations": 2,
          "covers": 17,
          "revenue": 962.0
        },
        "Comp Celebration (house), Likes DJ Music, Near DJ requested, Female birthday": {
          "reservations": 1,
          "covers": 3,
          "revenue": 0.0
        },
        "Celebration Package (unpaid), Cake in fridge": {
          "reservations": 1,
          "covers": 9,
          "revenue": 605.52
        },
        "Celebration Package (paid), Birthday, Father's Day": {
          "reservations": 1,
          "covers": 4,
          "revenue": 0.0
        },
        "Celebration, #GiganteThursdays": {
          "reservations": 1,
          "covers": 5,
          "revenue": 0.0
        },
        "G Room buyout, Cake in fridge": {
          "reservations": 1,
          "covers": 40,
          "revenue": 1923.0
        },
        "Expects VIP treatment": {
          "reservations": 2,
          "covers": 29,
          "revenue": 887.0
        },
        "Celebration Package (unpaid), Birthday": {
          "reservations": 1,
          "covers": 7,
          "revenue": 593.52
        },
        "Female birthday, Comp Celebration (house)": {
          "reservations": 1,
          "covers": 14,
          "revenue": 989.0
        },
        "Celebration Package (paid), Patio requested, Female birthday": {
          "reservations": 1,
          "covers": 8,
          "revenue": 485.0
        },
        "Female birthday, Celebration Package (unpaid), Cake in fridge": {
          "reservations": 1,
          "covers": 15,
          "revenue": 343.0
        },
        "Patio requested, Birthday, Celebration Package (paid)": {
          "reservations": 1,
          "covers": 6,
          "revenue": 521.0
        },
        "G Room buyout, Sweet 16": {
          "reservations": 1,
          "covers": 75,
          "revenue": 52.0
        },
        "Birthday, Celebration Package (paid)": {
          "reservations": 1,
          "covers": 3,
          "revenue": 0.0
        },
        "Female birthday, #GiganteThursdays, Celebration Package (paid), Shellfish": {
          "reservations": 1,
          "covers": 5,
          "revenue": 464.0
        },
        "Special event, Patio requested": {
          "reservations": 2,
          "covers": 5,
          "revenue": 0.0
        },
        "Bridal shower": {
          "reservations": 1,
          "covers": 32,
          "revenue": 0.0
        },
        "DJ Event, Comp check (house)": {
          "reservations": 1,
          "covers": 4,
          "revenue": 0.0
        },
        "Patio requested, Celebration Package (paid)": {
          "reservations": 1,
          "covers": 3,
          "revenue": 369.0
        },
        "Shellfish, Birthday, Celebration Package (paid), Expects VIP treatment": {
          "reservations": 1,
          "covers": 4,
          "revenue": 289.0
        },
        "Patio requested, Birthday, Celebration Package (unpaid), Cake in fridge": {
          "reservations": 1,
          "covers": 6,
          "revenue": 398.0
        },
        "Father's Day, Patio requested, Birthday": {
          "reservations": 1,
          "covers": 2,
          "revenue": 0.0
        },
        "Surprise Party, Male birthday, Cake in fridge, PDR - Buyout": {
          "reservations": 1,
          "covers": 15,
          "revenue": 2222.0
        },
        "Patio requested, Father's Day, Celebration Package (paid)": {
          "reservations": 1,
          "covers": 4,
          "revenue": 0.0
        },
        "Celebration, Patio requested, Father's Day": {
          "reservations": 1,
          "covers": 4,
          "revenue": 0.0
        },
        "Shrimp": {
          "reservations": 1,
          "covers": 2,
          "revenue": 0.0
        },
        "#GiganteThursdays, Birthday, Celebration Package (paid)": {
          "reservations": 1,
          "covers": 7,
          "revenue": 559.0
        },
        "Birthday, Celebration Package (unpaid), Cake in fridge": {
          "reservations": 1,
          "covers": 15,
          "revenue": 1299.52
        },
        "VIP Table/Bottle Service (preselected), DJ Event": {
          "reservations": 1,
          "covers": 4,
          "revenue": 0.0
        },
        "VIP Table/Bottle Service (preselected), Expects VIP treatment": {
          "reservations": 1,
          "covers": 6,
          "revenue": 0.0
        },
        "Father's Day, Birthday": {
          "reservations": 1,
          "covers": 2,
          "revenue": 0.0
        },
        "Comp round of drinks (house)": {
          "reservations": 1,
          "covers": 6,
          "revenue": 206.0
        },
        "Celebration Package (paid), Birthday": {
          "reservations": 1,
          "covers": 4,
          "revenue": 242.0
        },
        "Girls night": {
          "reservations": 1,
          "covers": 4,
          "revenue": 438.0
        }
      },
      "by_status": {
        "COMPLETE": 140,
        "CANCELED": 30,
        "PAID": 11,
        "NO_SHOW": 9,
        "ARRIVED": 29,
        "ARRIVED_PARTIAL": 1,
        "CONFIRMED": 2,
        "LATE": 1,
        "NOT_RECONCILED": 1
      },
      "by_day_of_week": {
        "Saturday": {
          "reservations": 62,
          "covers": 424,
          "revenue": 17065.1
        },
        "Friday": {
          "reservations": 67,
          "covers": 378,
          "revenue": 13647.600000000002
        },
        "Sunday": {
          "reservations": 58,
          "covers": 447,
          "revenue": 8249.0
        },
        "Thursday": {
          "reservations": 27,
          "covers": 151,
          "revenue": 3700.04
        },
        "Tuesday": {
          "reservations": 4,
          "covers": 32,
          "revenue": 445.0
        },
        "Wednesday": {
          "reservations": 6,
          "covers": 61,
          "revenue": 1079.0
        }
      },
      "top_tables": {
        "73": {
          "reservations": 4,
          "covers": 11,
          "revenue": 711.0
        },
        "27": {
          "reservations": 9,
          "covers": 41,
          "revenue": 1259.0
        },
        "28": {
          "reservations": 9,
          "covers": 38,
          "revenue": 795.0
        },
        "26": {
          "reservations": 6,
          "covers": 33,
          "revenue": 862.0
        },
        "62": {
          "reservations": 9,
          "covers": 53,
          "revenue": 2217.52
        },
        "21": {
          "reservations": 3,
          "covers": 12,
          "revenue": 0.0
        },
        "22": {
          "reservations": 4,
          "covers": 18,
          "revenue": 206.0
        },
        "58": {
          "reservations": 9,
          "covers": 42,
          "revenue": 2330.52
        },
        "56": {
          "reservations": 6,
          "covers": 36,
          "revenue": 2672.52
        },
        "57": {
          "reservations": 9,
          "covers": 46,
          "revenue": 2763.52
        },
        "55": {
          "reservations": 4,
          "covers": 22,
          "revenue": 1353.52
        },
        "90": {
          "reservations": 10,
          "covers": 401,
          "revenue": 4837.0
        },
        "81": {
          "reservations": 10,
          "covers": 392,
          "revenue": 4166.0
        },
        "24": {
          "reservations": 9,
          "covers": 32,
          "revenue": 496.0
        },
        "23": {
          "reservations": 7,
          "covers": 28,
          "revenue": 333.0
        },
        "V11": {
          "reservations": 1,
          "covers": 8,
          "revenue": 0.0
        },
        "93": {
          "reservations": 7,
          "covers": 298,
          "revenue": 2572.0
        },
        "60": {
          "reservations": 9,
          "covers": 119,
          "revenue": 6328.040000000001
        },
        "14": {
          "reservations": 1,
          "covers": 3,
          "revenue": 168.0
        },
        "25": {
          "reservations": 5,
          "covers": 19,
          "revenue": 955.52
        },
        "91": {
          "reservations": 9,
          "covers": 389,
          "revenue": 4166.0
        },
        "92": {
          "reservations": 10,
          "covers": 392,
          "revenue": 4482.0
        },
        "83": {
          "reservations": 8,
          "covers": 384,
          "revenue": 4166.0
        },
        "82": {
          "reservations": 9,
          "covers": 388,
          "revenue": 4166.0
        },
        "80": {
          "reservations": 8,
          "covers": 384,
          "revenue": 4166.0
        },
        "205": {
          "reservations": 9,
          "covers": 321,
          "revenue": 3569.0
        },
        "V6": {
          "reservations": 1,
          "covers": 2,
          "revenue": 0.0
        },
        "29": {
          "reservations": 7,
          "covers": 16,
          "revenue": 323.0
        },
        "70": {
          "reservations": 5,
          "covers": 26,
          "revenue": 1795.52
        },
        "30": {
          "reservations": 13,
          "covers": 116,
          "revenue": 5075.04
        },
        "40u": {
          "reservations": 7,
          "covers": 58,
          "revenue": 1993.0
        },
        "103": {
          "reservations": 2,
          "covers": 82,
          "revenue": 52.0
        },
        "52": {
          "reservations": 8,
          "covers": 36,
          "revenue": 2339.04
        },
        "51": {
          "reservations": 7,
          "covers": 30,
          "revenue": 1834.04
        },
        "20": {
          "reservations": 12,
          "covers": 24,
          "revenue": 980.5
        },
        "59": {
          "reservations": 10,
          "covers": 20,
          "revenue": 361.0
        },
        "V16": {
          "reservations": 1,
          "covers": 3,
          "revenue": 0.0
        },
        "11": {
          "reservations": 6,
          "covers": 58,
          "revenue": 3245.52
        },
        "10": {
          "reservations": 7,
          "covers": 50,
          "revenue": 2244.52
        },
        "3": {
          "reservations": 4,
          "covers": 53,
          "revenue": 3171.0
        },
        "4": {
          "reservations": 3,
          "covers": 49,
          "revenue": 3171.0
        },
        "1": {
          "reservations": 4,
          "covers": 52,
          "revenue": 3171.0
        },
        "5": {
          "reservations": 3,
          "covers": 49,
          "revenue": 3171.0
        },
        "2": {
          "reservations": 3,
          "covers": 49,
          "revenue": 3171.0
        },
        "53": {
          "reservations": 9,
          "covers": 40,
          "revenue": 2332.52
        },
        "663": {
          "reservations": 3,
          "covers": 8,
          "revenue": 636.0
        },
        "54": {
          "reservations": 4,
          "covers": 16,
          "revenue": 1328.52
        },
        "13": {
          "reservations": 7,
          "covers": 39,
          "revenue": 1494.0
        },
        "12": {
          "reservations": 7,
          "covers": 53,
          "revenue": 2625.52
        },
        "V12": {
          "reservations": 1,
          "covers": 8,
          "revenue": 0.0
        },
        "71": {
          "reservations": 3,
          "covers": 18,
          "revenue": 1137.0
        },
        "V5": {
          "reservations": 1,
          "covers": 6,
          "revenue": 0.0
        },
        "61": {
          "reservations": 9,
          "covers": 120,
          "revenue": 6107.04
        },
        "V1": {
          "reservations": 1,
          "covers": 9,
          "revenue": 0.0
        },
        "50": {
          "reservations": 5,
          "covers": 11,
          "revenue": 558.0
        },
        "101": {
          "reservations": 2,
          "covers": 79,
          "revenue": 52.0
        },
        "72": {
          "reservations": 1,
          "covers": 3,
          "revenue": 182.0
        },
        "Bar7": {
          "reservations": 1,
          "covers": 5,
          "revenue": 0.0
        },
        "Bar8": {
          "reservations": 1,
          "covers": 5,
          "revenue": 0.0
        },
        "Bar9": {
          "reservations": 1,
          "covers": 5,
          "revenue": 0.0
        },
        "L1": {
          "reservations": 2,
          "covers": 10,
          "revenue": 293.0
        },
        "V2": {
          "reservations": 1,
          "covers": 8,
          "revenue": 0.0
        },
        "SAB 2": {
          "reservations": 1,
          "covers": 8,
          "revenue": 0.0
        },
        "100": {
          "reservations": 1,
          "covers": 75,
          "revenue": 52.0
        },
        "102": {
          "reservations": 1,
          "covers": 75,
          "revenue": 52.0
        },
        "110": {
          "reservations": 1,
          "covers": 75,
          "revenue": 52.0
        },
        "113": {
          "reservations": 1,
          "covers": 75,
          "revenue": 52.0
        },
        "112": {
          "reservations": 1,
          "covers": 75,
          "revenue": 52.0
        },
        "111": {
          "reservations": 1,
          "covers": 75,
          "revenue": 52.0
        },
        "V10": {
          "reservations": 1,
          "covers": 4,
          "revenue": 0.0
        },
        "Bar3": {
          "reservations": 1,
          "covers": 2,
          "revenue": 0.0
        },
        "Bar4": {
          "reservations": 1,
          "covers": 2,
          "revenue": 0.0
        },
        "15": {
          "reservations": 1,
          "covers": 4,
          "revenue": 289.0
        },
        "V9": {
          "reservations": 1,
          "covers": 4,
          "revenue": 0.0
        },
        "V7": {
          "reservations": 1,
          "covers": 6,
          "revenue": 0.0
        }
      }
    },
    "previous_period": {
      "total_reservations": 106,
      "total_covers": 671,
      "no_shows": 9,
      "cancellations": 14,
      "completed": 83,
      "vip_count": 4,
      "total_revenue": 28801.15,
      "total_gross_revenue": 35866.99,
      "total_prepayment": 394.11,
      "avg_party_size": 6.3,
      "avg_duration_min": 143.0,
      "by_server": {
        "Ana": {
          "reservations": 21,
          "covers": 101,
          "revenue": 7208.99
        },
        "Drilon": {
          "reservations": 11,
          "covers": 92,
          "revenue": 5423.040000000001
        },
        "Daniel": {
          "reservations": 11,
          "covers": 52,
          "revenue": 3570.96
        },
        "Florencio": {
          "reservations": 7,
          "covers": 80,
          "revenue": 3292.0
        },
        "Errol": {
          "reservations": 6,
          "covers": 45,
          "revenue": 3089.56
        },
        "Fab": {
          "reservations": 6,
          "covers": 54,
          "revenue": 1582.52
        },
        "Gabi": {
          "reservations": 7,
          "covers": 64,
          "revenue": 830.52
        },
        "Brianna": {
          "reservations": 3,
          "covers": 15,
          "revenue": 404.52
        },
        "Angela": {
          "reservations": 4,
          "covers": 21,
          "revenue": 357.0
        },
        "Bar": {
          "reservations": 2,
          "covers": 10,
          "revenue": 0.0
        },
        "Tianna": {
          "reservations": 1,
          "covers": 4,
          "revenue": 0.0
        },
        "Jess": {
          "reservations": 1,
          "covers": 6,
          "revenue": 0.0
        },
        "Junior": {
          "reservations": 1,
          "covers": 3,
          "revenue": 0.0
        },
        "Chris Luna": {
          "reservations": 1,
          "covers": 2,
          "revenue": 0.0
        }
      },
      "by_day": {
        "2026-06-03": {
          "reservations": 1,
          "covers": 2,
          "revenue": 0.0
        },
        "2026-06-13": {
          "reservations": 14,
          "covers": 102,
          "revenue": 3833.6
        },
        "2026-06-12": {
          "reservations": 6,
          "covers": 54,
          "revenue": 704.0
        },
        "2026-05-24": {
          "reservations": 5,
          "covers": 38,
          "revenue": 0.0
        },
        "2026-06-05": {
          "reservations": 2,
          "covers": 10,
          "revenue": 1062.0
        },
        "2026-05-21": {
          "reservations": 6,
          "covers": 40,
          "revenue": 1799.0
        },
        "2026-05-22": {
          "reservations": 8,
          "covers": 32,
          "revenue": 2949.52
        },
        "2026-06-19": {
          "reservations": 6,
          "covers": 43,
          "revenue": 4749.0
        },
        "2026-05-31": {
          "reservations": 4,
          "covers": 18,
          "revenue": 0.0
        },
        "2026-06-06": {
          "reservations": 9,
          "covers": 26,
          "revenue": 1028.0
        },
        "2026-05-30": {
          "reservations": 8,
          "covers": 44,
          "revenue": 2446.4700000000003
        },
        "2026-06-18": {
          "reservations": 12,
          "covers": 61,
          "revenue": 3877.04
        },
        "2026-06-04": {
          "reservations": 2,
          "covers": 34,
          "revenue": 87.0
        },
        "2026-06-16": {
          "reservations": 3,
          "covers": 6,
          "revenue": 133.0
        },
        "2026-06-14": {
          "reservations": 4,
          "covers": 68,
          "revenue": 3530.52
        },
        "2026-05-27": {
          "reservations": 1,
          "covers": 5,
          "revenue": 289.0
        },
        "2026-05-23": {
          "reservations": 5,
          "covers": 18,
          "revenue": 1419.48
        },
        "2026-05-29": {
          "reservations": 2,
          "covers": 10,
          "revenue": 553.52
        },
        "2026-06-07": {
          "reservations": 3,
          "covers": 37,
          "revenue": 0.0
        },
        "2026-06-02": {
          "reservations": 1,
          "covers": 3,
          "revenue": 146.0
        },
        "2026-05-28": {
          "reservations": 2,
          "covers": 8,
          "revenue": 194.0
        },
        "2026-06-11": {
          "reservations": 2,
          "covers": 12,
          "revenue": 0.0
        }
      },
      "by_shift": {
        "DINNER": {
          "reservations": 90,
          "covers": 510,
          "revenue": 25270.630000000005
        },
        "BRUNCH": {
          "reservations": 16,
          "covers": 161,
          "revenue": 3530.52
        }
      },
      "by_seating_area": {
        "Patio 2": {
          "reservations": 3,
          "covers": 12,
          "revenue": 0.0
        },
        "Main Dining": {
          "reservations": 70,
          "covers": 368,
          "revenue": 17544.63
        },
        "G Room": {
          "reservations": 14,
          "covers": 99,
          "revenue": 3646.48
        },
        "Patio 1": {
          "reservations": 5,
          "covers": 12,
          "revenue": 607.0
        },
        "PDR": {
          "reservations": 5,
          "covers": 115,
          "revenue": 6457.52
        },
        "Unknown": {
          "reservations": 6,
          "covers": 49,
          "revenue": 426.52
        },
        "Poolside VIP Nightlife Table": {
          "reservations": 1,
          "covers": 6,
          "revenue": 0.0
        },
        "Grand Ballroom (Mulino\u2019s)": {
          "reservations": 2,
          "covers": 10,
          "revenue": 119.0
        }
      },
      "by_reservation_type": {
        "Celebration Package (unpaid)": {
          "reservations": 4,
          "covers": 29,
          "revenue": 2281.4300000000003
        },
        "Standard": {
          "reservations": 44,
          "covers": 225,
          "revenue": 7605.04
        },
        "Patio requested, Birthday, Celebration Package (paid)": {
          "reservations": 1,
          "covers": 7,
          "revenue": 704.0
        },
        "#GiganteThursdays": {
          "reservations": 1,
          "covers": 5,
          "revenue": 397.0
        },
        "Birthday": {
          "reservations": 13,
          "covers": 54,
          "revenue": 1602.0
        },
        "Patio requested": {
          "reservations": 5,
          "covers": 10,
          "revenue": 250.0
        },
        "Pool Party, Graduation": {
          "reservations": 1,
          "covers": 4,
          "revenue": 254.52
        },
        "Female birthday, Main room requested, Cake in fridge": {
          "reservations": 1,
          "covers": 21,
          "revenue": 2811.0
        },
        "Pool Party, VIP Table/Bottle Service (preselected)": {
          "reservations": 2,
          "covers": 10,
          "revenue": 0.0
        },
        "Birthday, Pool Party": {
          "reservations": 1,
          "covers": 2,
          "revenue": 160.0
        },
        "Cake in fridge, Celebration Package (unpaid)": {
          "reservations": 1,
          "covers": 12,
          "revenue": 830.52
        },
        "Birthday, Patio requested": {
          "reservations": 1,
          "covers": 5,
          "revenue": 289.0
        },
        "Celebration Package (paid)": {
          "reservations": 1,
          "covers": 2,
          "revenue": 133.0
        },
        "Graduation, Congratulations, PDR - Buyout": {
          "reservations": 1,
          "covers": 20,
          "revenue": 1484.0
        },
        "Patio requested, Birthday": {
          "reservations": 1,
          "covers": 12,
          "revenue": 0.0
        },
        "Graduation, Celebration Package (unpaid)": {
          "reservations": 1,
          "covers": 5,
          "revenue": 486.52
        },
        "Birthday, See notes, Cake in fridge": {
          "reservations": 1,
          "covers": 16,
          "revenue": 2162.52
        },
        "Birthday, Cake in fridge": {
          "reservations": 1,
          "covers": 9,
          "revenue": 774.0
        },
        "Pool Party": {
          "reservations": 4,
          "covers": 10,
          "revenue": 351.0
        },
        "Birthday, Celebration Package (unpaid)": {
          "reservations": 2,
          "covers": 8,
          "revenue": 841.52
        },
        "Female birthday": {
          "reservations": 1,
          "covers": 14,
          "revenue": 406.52
        },
        "Celebration Package (unpaid), PDR - Buyout": {
          "reservations": 1,
          "covers": 32,
          "revenue": 0.0
        },
        "Male birthday": {
          "reservations": 1,
          "covers": 32,
          "revenue": 87.0
        },
        "Patio requested, Anniversary": {
          "reservations": 1,
          "covers": 2,
          "revenue": 0.0
        },
        "Patio requested, Graduation": {
          "reservations": 1,
          "covers": 8,
          "revenue": 0.0
        },
        "Patio lounge requested, Patio requested": {
          "reservations": 1,
          "covers": 4,
          "revenue": 0.0
        },
        "Graduation": {
          "reservations": 3,
          "covers": 20,
          "revenue": 659.52
        },
        "ESPRESSO MARTINI TREE (8), Birthday, Celebration Package (unpaid)": {
          "reservations": 1,
          "covers": 6,
          "revenue": 279.0
        },
        "Birthday, DJ music, Near DJ requested": {
          "reservations": 1,
          "covers": 14,
          "revenue": 923.52
        },
        "Engagement": {
          "reservations": 1,
          "covers": 4,
          "revenue": 575.0
        },
        "Graduation, Congratulations": {
          "reservations": 1,
          "covers": 5,
          "revenue": 0.0
        },
        "Congratulations, Anniversary": {
          "reservations": 1,
          "covers": 2,
          "revenue": 283.0
        },
        "Patio requested, Celebration Package (paid), Birthday, Cake in fridge": {
          "reservations": 1,
          "covers": 12,
          "revenue": 0.0
        },
        "Celebration Package (unpaid), Birthday, Near DJ requested, ESPRESSO MARTINI TREE (8), Cake in fridge": {
          "reservations": 1,
          "covers": 11,
          "revenue": 1258.0
        },
        "Female birthday, PDR - Buyout": {
          "reservations": 1,
          "covers": 26,
          "revenue": 0.0
        },
        "See notes": {
          "reservations": 1,
          "covers": 4,
          "revenue": 0.0
        },
        "Graduation, Birthday, Celebration Package (unpaid)": {
          "reservations": 1,
          "covers": 9,
          "revenue": 912.52
        }
      },
      "by_status": {
        "COMPLETE": 65,
        "NO_SHOW": 9,
        "ARRIVED": 12,
        "CANCELED": 14,
        "PAID": 5,
        "CONFIRMED": 1
      },
      "by_day_of_week": {
        "Wednesday": {
          "reservations": 2,
          "covers": 7,
          "revenue": 289.0
        },
        "Saturday": {
          "reservations": 36,
          "covers": 190,
          "revenue": 8727.55
        },
        "Friday": {
          "reservations": 24,
          "covers": 149,
          "revenue": 10018.04
        },
        "Sunday": {
          "reservations": 16,
          "covers": 161,
          "revenue": 3530.52
        },
        "Thursday": {
          "reservations": 24,
          "covers": 155,
          "revenue": 5957.04
        },
        "Tuesday": {
          "reservations": 4,
          "covers": 9,
          "revenue": 279.0
        }
      },
      "top_tables": {
        "110": {
          "reservations": 1,
          "covers": 2,
          "revenue": 0.0
        },
        "30": {
          "reservations": 3,
          "covers": 28,
          "revenue": 704.0
        },
        "40u": {
          "reservations": 4,
          "covers": 36,
          "revenue": 426.52
        },
        "92": {
          "reservations": 4,
          "covers": 11,
          "revenue": 721.0
        },
        "58": {
          "reservations": 4,
          "covers": 19,
          "revenue": 397.0
        },
        "56": {
          "reservations": 2,
          "covers": 10,
          "revenue": 397.0
        },
        "57": {
          "reservations": 4,
          "covers": 19,
          "revenue": 397.0
        },
        "60": {
          "reservations": 3,
          "covers": 15,
          "revenue": 404.52
        },
        "101": {
          "reservations": 1,
          "covers": 6,
          "revenue": 0.0
        },
        "62": {
          "reservations": 4,
          "covers": 27,
          "revenue": 2029.43
        },
        "73": {
          "reservations": 3,
          "covers": 8,
          "revenue": 492.0
        },
        "24": {
          "reservations": 5,
          "covers": 64,
          "revenue": 2700.0
        },
        "23": {
          "reservations": 5,
          "covers": 67,
          "revenue": 3062.52
        },
        "29": {
          "reservations": 7,
          "covers": 14,
          "revenue": 157.0
        },
        "59": {
          "reservations": 4,
          "covers": 8,
          "revenue": 395.0
        },
        "11": {
          "reservations": 5,
          "covers": 81,
          "revenue": 4779.04
        },
        "3": {
          "reservations": 5,
          "covers": 115,
          "revenue": 6457.52
        },
        "4": {
          "reservations": 5,
          "covers": 115,
          "revenue": 6457.52
        },
        "1": {
          "reservations": 5,
          "covers": 115,
          "revenue": 6457.52
        },
        "5": {
          "reservations": 5,
          "covers": 115,
          "revenue": 6457.52
        },
        "2": {
          "reservations": 5,
          "covers": 115,
          "revenue": 6457.52
        },
        "12": {
          "reservations": 5,
          "covers": 84,
          "revenue": 5677.040000000001
        },
        "T3": {
          "reservations": 1,
          "covers": 4,
          "revenue": 0.0
        },
        "54": {
          "reservations": 5,
          "covers": 23,
          "revenue": 1378.52
        },
        "50": {
          "reservations": 5,
          "covers": 10,
          "revenue": 602.52
        },
        "53": {
          "reservations": 4,
          "covers": 21,
          "revenue": 1378.52
        },
        "52": {
          "reservations": 3,
          "covers": 20,
          "revenue": 1260.52
        },
        "51": {
          "reservations": 3,
          "covers": 20,
          "revenue": 1260.52
        },
        "27": {
          "reservations": 4,
          "covers": 23,
          "revenue": 1782.52
        },
        "28": {
          "reservations": 4,
          "covers": 20,
          "revenue": 1352.52
        },
        "26": {
          "reservations": 5,
          "covers": 26,
          "revenue": 1940.52
        },
        "82": {
          "reservations": 4,
          "covers": 16,
          "revenue": 1207.96
        },
        "55": {
          "reservations": 1,
          "covers": 2,
          "revenue": 0.0
        },
        "14": {
          "reservations": 2,
          "covers": 54,
          "revenue": 2988.0
        },
        "13": {
          "reservations": 3,
          "covers": 60,
          "revenue": 3186.52
        },
        "SAB 2": {
          "reservations": 1,
          "covers": 6,
          "revenue": 0.0
        },
        "21": {
          "reservations": 4,
          "covers": 63,
          "revenue": 3275.52
        },
        "22": {
          "reservations": 4,
          "covers": 63,
          "revenue": 3275.52
        },
        "205": {
          "reservations": 2,
          "covers": 10,
          "revenue": 119.0
        },
        "10": {
          "reservations": 3,
          "covers": 75,
          "revenue": 4364.52
        },
        "28-58": {
          "reservations": 1,
          "covers": 2,
          "revenue": 0.0
        },
        "25": {
          "reservations": 4,
          "covers": 21,
          "revenue": 1651.52
        },
        "83": {
          "reservations": 1,
          "covers": 2,
          "revenue": 234.0
        },
        "663": {
          "reservations": 2,
          "covers": 7,
          "revenue": 0.0
        },
        "91": {
          "reservations": 1,
          "covers": 32,
          "revenue": 87.0
        },
        "90": {
          "reservations": 1,
          "covers": 32,
          "revenue": 87.0
        },
        "81": {
          "reservations": 3,
          "covers": 52,
          "revenue": 1289.52
        },
        "80": {
          "reservations": 3,
          "covers": 52,
          "revenue": 1204.52
        },
        "70": {
          "reservations": 2,
          "covers": 4,
          "revenue": 115.0
        },
        "100": {
          "reservations": 1,
          "covers": 4,
          "revenue": 0.0
        },
        "20": {
          "reservations": 1,
          "covers": 50,
          "revenue": 2700.0
        },
        "15": {
          "reservations": 1,
          "covers": 50,
          "revenue": 2700.0
        },
        "61": {
          "reservations": 3,
          "covers": 22,
          "revenue": 1902.43
        },
        "93": {
          "reservations": 1,
          "covers": 12,
          "revenue": 0.0
        }
      }
    },
    "comparison": {
      "total_reservations": {
        "label": "Reservations",
        "current": 224,
        "previous": 106,
        "delta": 118,
        "pct_change": 111.3,
        "direction": "up"
      },
      "total_covers": {
        "label": "Covers",
        "current": 1493,
        "previous": 671,
        "delta": 822,
        "pct_change": 122.5,
        "direction": "up"
      },
      "total_revenue": {
        "label": "Net Revenue",
        "current": 44185.74,
        "previous": 28801.15,
        "delta": 15384.59,
        "pct_change": 53.4,
        "direction": "up"
      },
      "total_gross_revenue": {
        "label": "Gross Revenue",
        "current": 56017.76,
        "previous": 35866.99,
        "delta": 20150.77,
        "pct_change": 56.2,
        "direction": "up"
      },
      "no_shows": {
        "label": "No Shows",
        "current": 9,
        "previous": 9,
        "delta": 0,
        "pct_change": 0.0,
        "direction": "flat"
      },
      "cancellations": {
        "label": "Cancellations",
        "current": 30,
        "previous": 14,
        "delta": 16,
        "pct_change": 114.3,
        "direction": "up"
      },
      "completed": {
        "label": "Completed",
        "current": 185,
        "previous": 83,
        "delta": 102,
        "pct_change": 122.9,
        "direction": "up"
      },
      "vip_count": {
        "label": "VIP Guests",
        "current": 4,
        "previous": 4,
        "delta": 0,
        "pct_change": 0.0,
        "direction": "flat"
      },
      "avg_party_size": {
        "label": "Avg Party Size",
        "current": 6.7,
        "previous": 6.3,
        "delta": 0.4,
        "pct_change": 6.3,
        "direction": "up"
      },
      "avg_duration_min": {
        "label": "Avg Duration (min)",
        "current": 139.0,
        "previous": 143.0,
        "delta": -4.0,
        "pct_change": -2.8,
        "direction": "down"
      },
      "server_changes": {
        "Florencio": {
          "current_revenue": 9889.0,
          "previous_revenue": 3292.0,
          "delta": 6597.0,
          "current_covers": 279,
          "previous_covers": 80
        },
        "Daniel": {
          "current_revenue": 8923.08,
          "previous_revenue": 3570.96,
          "delta": 5352.12,
          "current_covers": 328,
          "previous_covers": 52
        },
        "Drilon": {
          "current_revenue": 8926.56,
          "previous_revenue": 5423.04,
          "delta": 3503.52,
          "current_covers": 120,
          "previous_covers": 92
        },
        "Angela": {
          "current_revenue": 2975.56,
          "previous_revenue": 357.0,
          "delta": 2618.56,
          "current_covers": 40,
          "previous_covers": 21
        },
        "Gabi": {
          "current_revenue": 2095.0,
          "previous_revenue": 830.52,
          "delta": 1264.48,
          "current_covers": 62,
          "previous_covers": 64
        },
        "Junior": {
          "current_revenue": 614.0,
          "previous_revenue": 0.0,
          "delta": 614.0,
          "current_covers": 22,
          "previous_covers": 3
        },
        "Chris Luna": {
          "current_revenue": 282.0,
          "previous_revenue": 0.0,
          "delta": 282.0,
          "current_covers": 32,
          "previous_covers": 2
        },
        "Errol": {
          "current_revenue": 3337.04,
          "previous_revenue": 3089.56,
          "delta": 247.48,
          "current_covers": 72,
          "previous_covers": 45
        },
        "Bar": {
          "current_revenue": 0,
          "previous_revenue": 0.0,
          "delta": 0.0,
          "current_covers": 0,
          "previous_covers": 10
        },
        "Tianna": {
          "current_revenue": 0,
          "previous_revenue": 0.0,
          "delta": 0.0,
          "current_covers": 0,
          "previous_covers": 4
        },
        "Grace": {
          "current_revenue": 0.0,
          "previous_revenue": 0,
          "delta": 0.0,
          "current_covers": 39,
          "previous_covers": 0
        },
        "Jess": {
          "current_revenue": 0.0,
          "previous_revenue": 0.0,
          "delta": 0.0,
          "current_covers": 19,
          "previous_covers": 6
        },
        "Fab": {
          "current_revenue": 1193.0,
          "previous_revenue": 1582.52,
          "delta": -389.52,
          "current_covers": 137,
          "previous_covers": 54
        },
        "Brianna": {
          "current_revenue": 0,
          "previous_revenue": 404.52,
          "delta": -404.52,
          "current_covers": 0,
          "previous_covers": 15
        },
        "Ana": {
          "current_revenue": 4244.5,
          "previous_revenue": 7208.99,
          "delta": -2964.49,
          "current_covers": 91,
          "previous_covers": 101
        }
      },
      "day_of_week_changes": {
        "Monday": {
          "current_revenue": 0,
          "previous_revenue": 0,
          "current_covers": 0,
          "previous_covers": 0
        },
        "Tuesday": {
          "current_revenue": 445.0,
          "previous_revenue": 279.0,
          "current_covers": 32,
          "previous_covers": 9
        },
        "Wednesday": {
          "current_revenue": 1079.0,
          "previous_revenue": 289.0,
          "current_covers": 61,
          "previous_covers": 7
        },
        "Thursday": {
          "current_revenue": 3700.04,
          "previous_revenue": 5957.04,
          "current_covers": 151,
          "previous_covers": 155
        },
        "Friday": {
          "current_revenue": 13647.6,
          "previous_revenue": 10018.04,
          "current_covers": 378,
          "previous_covers": 149
        },
        "Saturday": {
          "current_revenue": 17065.1,
          "previous_revenue": 8727.55,
          "current_covers": 424,
          "previous_covers": 190
        },
        "Sunday": {
          "current_revenue": 8249.0,
          "previous_revenue": 3530.52,
          "current_covers": 447,
          "previous_covers": 161
        }
      }
    }
  },
  "tripleseat": {},
  "errors": [
    "Toast: Authentication failed",
    "Tripleseat: Authentication failed"
  ]
}